mui/__init__.py
mui/utility.py
mui/components/__init__.py
mui/components/attributes.py
mui/components/base.py
mui/components/component.py
mui/components/elements.py
mui/components/forms/__init__.py
mui/components/forms/mui_form.py
mui/components/state/__init__.py
mui/components/state/component_state.py
mui/components/state/props.py
mui/components/tag_classes/__init__.py
mui/components/tag_classes/block_tags.py
mui/components/tag_classes/self_closing.py
mui/components/tag_functions/__init__.py
mui/components/tag_functions/block_tags.py
mui/components/tag_functions/self_closing.py
mui/context/__init__.py
mui/context/context_logic.py
mui/context/django.py
mui/htmx/__init__.py
mui/htmx/htmx.py
mui/htmx/htmx_enum.py
mui/request/__init__.py
mui/request/props.py
mui/request/request_context.py
mui/request/transformer.py
mui/shortcuts/__init__.py
mui/shortcuts/configs.py
mui/shortcuts/shortcuts.py
mui/shortcuts/shortcuts_utils.py
mui/styles/__init__.py
mui/styles/css_enum.py
mui/styles/elements.py
mui/styles/plain_css.py
mui/styles/utils.py
mui/styles/frameworks/__init__.py
mui/styles/frameworks/base_frame.py
mui/styles/frameworks/bs5/__init__.py
mui/styles/frameworks/bs5/bs5.py
mui/styles/frameworks/bs5/content.py
mui/styles/frameworks/bs5/custom.py
mui/styles/frameworks/bs5/extend.py
mui/styles/frameworks/bs5/forms.py
mui/styles/frameworks/bs5/layout.py
mui/styles/frameworks/bs5/typography.py
mui/styles/frameworks/bs5/utilities.py
mui/styles/frameworks/bs5/components/__init__.py
mui/styles/frameworks/bs5/components/bs5_comp.py
mui/styles/frameworks/bs5/components/comp_enum.py
mui/styles/frameworks/bs5/components/defaults/__init__.py
mui/styles/frameworks/bs5/components/defaults/accordion.py
mui/styles/frameworks/bs5/components/defaults/alert.py
mui/styles/frameworks/bs5/components/defaults/badge.py
mui/styles/frameworks/bs5/components/defaults/breadcrumb.py
mui/styles/frameworks/bs5/components/defaults/button.py
mui/styles/frameworks/bs5/components/defaults/card.py
mastodon_ui-1.0.6.dist-info/METADATA
mastodon_ui-1.0.6.dist-info/WHEEL
mastodon_ui-1.0.6.dist-info/entry_points.txt
mastodon_ui-1.0.6.dist-info/licenses/LICENSE
mastodon_ui-1.0.6.dist-info/RECORD
