Metadata-Version: 2.4
Name: mastodon-ui
Version: 1.0.6
Summary: A declarative, type-safe ,Python-Native template Rendering Framework and Meta-framework for Django.
Project-URL: Homepage, https://github.com/MojahiD-0-YouneSS/mastodon-ui
Project-URL: Bug Tracker, https://github.com/MojahiD-0-YouneSS/mastodon-ui/issues
Project-URL: Documentation, https://MojahiD-0-YouneSS.github.io/mastodon-ui/
Project-URL: Funding, https://ko-fi.com/youness_mojahid
Author-email: Youness Mojahid <mojahidyouness0@gmail.com>
License: MIT License
License-File: LICENSE
Classifier: Framework :: Django
Classifier: License :: OSI Approved :: MIT License
Classifier: Operating System :: OS Independent
Classifier: Programming Language :: Python :: 3
Classifier: Topic :: Internet :: WWW/HTTP :: Dynamic Content
Classifier: Topic :: Software Development :: Libraries :: Python Modules
Requires-Python: >=3.9
Requires-Dist: cssutils>=2.11.1
Requires-Dist: lxml>=4.9.0
Requires-Dist: rich>=13.0.0
Requires-Dist: tinycss2>=1.2.0
Requires-Dist: typer>=0.9.0
